{"name":"Accessibilité numerique, mais au fait de quoi on parle ? – Conférence","tagline":"En parallèle de la conférence \"Accessibilité numérique, mais au fait de quoi on parle ?\"","body":"# À propos\r\n\r\nCette page a pour but de relayer les informations liée à la conférence \"Accessibilité numérique, mais au fait de quoi on parle ?\", présentée à Accessiday, le 28 mai 2014.\r\n\r\n# Liens et références","google":"","note":"Don't delete this file! It's used internally to help with page regeneration."}